CODE_OF_CONDUCT.md
CONTRIBUTING.md
LICENSE
MANIFEST.in
README.md
pyproject.toml
requirements.txt
setup.py
examples/__init__.py
examples/export_report.py
examples/get_all_messages.py
examples/list_sensors.py
wialon/__init__.py
wialon/auth_manager.py
wialon/errors.py
wialon/exchange.py
wialon/extra.py
wialon/items.py
wialon/messages.py
wialon/renderer.py
wialon/report.py
wialon/units.py
wialon/wialon.py
wialon_sdk.egg-info/PKG-INFO
wialon_sdk.egg-info/SOURCES.txt
wialon_sdk.egg-info/dependency_links.txt
wialon_sdk.egg-info/entry_points.txt
wialon_sdk.egg-info/requires.txt
wialon_sdk.egg-info/top_level.txt