Metadata-Version: 2.4
Name: wialon-sdk
Version: 0.5.2
Summary: Python SDK for Wialon API
Home-page: https://github.com/tetotille/wialon-sdk
Author: Jorge Tillería
Author-email: jltilleriam@gmail.com
Classifier: Programming Language :: Python :: 3
Classifier: License :: OSI Approved :: MIT License
Classifier: Operating System :: OS Independent
Requires-Python: >=3.8
License-File: LICENSE
Requires-Dist: requests>=2.32.3
Dynamic: author
Dynamic: author-email
Dynamic: classifier
Dynamic: description
Dynamic: description-content-type
Dynamic: home-page
Dynamic: license-file
Dynamic: requires-dist
Dynamic: requires-python
Dynamic: summary
